<annotation><path>Periparus_ater_1149_aug_188.jpg</path><source><database>Unknown</database><reviewresult></reviewresult><comment><admin></admin><subord></subord></comment></source><size><width>806</width><height>1024</height><depth>3</depth></size><segments>0</segments><object><name>PeriparusAter</name><pose>Unspecified</pose><truncated>0</truncated><difficult>0</difficult><bndbox><xmin>35.38093304228641</xmin><xmax>748.9944159602011</xmax><ymin>242.86146504898727</ymin><ymax>823.4001725975938</ymax></bndbox></object><folder>dataset</folder><filename>Periparus_ater_1149_aug_188.jpg</filename></annotation>