<annotation><path>Pica_pica_748_aug_34.jpg</path><source><database>Unknown</database><reviewresult></reviewresult><comment><admin></admin><subord></subord></comment></source><size><width>683</width><height>1024</height><depth>3</depth></size><segments>0</segments><object><name>PicaPica</name><pose>Unspecified</pose><truncated>0</truncated><difficult>0</difficult><bndbox><xmin>263.6439514972758</xmin><xmax>464.99580107328666</xmax><ymin>230.8834541804924</ymin><ymax>938.2996190242104</ymax></bndbox></object><folder>dataset</folder><filename>Pica_pica_748_aug_34.jpg</filename></annotation>