<annotation>
 <path>
  ErithacusRubecula1039.jpg
 </path>
 <source>
  <database>
   Unknown
  </database>
  <reviewresult>
  </reviewresult>
  <comment>
   <admin>
   </admin>
   <subord>
   </subord>
  </comment>
 </source>
 <size>
  <width>
   1024
  </width>
  <height>
   683
  </height>
  <depth>
   3
  </depth>
 </size>
 <segments>
  0
 </segments>
 <object>
  <name>
   ErithacusRubecula
  </name>
  <pose>
   Unspecified
  </pose>
  <truncated>
   0
  </truncated>
  <difficult>
   0
  </difficult>
  <bndbox>
   <xmin>
    513.4595710979265
   </xmin>
   <xmax>
    562.4041661261581
   </xmax>
   <ymin>
    325.49834433694963
   </ymin>
   <ymax>
    365.4896597868462
   </ymax>
  </bndbox>
 </object>
 <folder>
  dataset
 </folder>
 <filename>
  ErithacusRubecula1039.jpg
 </filename>
</annotation>