<annotation>
 <path>
  ErithacusRubecula0625.jpg
 </path>
 <source>
  <database>
   Unknown
  </database>
  <reviewresult>
  </reviewresult>
  <comment>
   <admin>
   </admin>
   <subord>
   </subord>
  </comment>
 </source>
 <size>
  <width>
   800
  </width>
  <height>
   647
  </height>
  <depth>
   3
  </depth>
 </size>
 <segments>
  0
 </segments>
 <object>
  <name>
   ErithacusRubecula
  </name>
  <pose>
   Unspecified
  </pose>
  <truncated>
   0
  </truncated>
  <difficult>
   0
  </difficult>
  <bndbox>
   <xmin>
    366.89175718762584
   </xmin>
   <xmax>
    414.9528221374098
   </xmax>
   <ymin>
    290.24819242559755
   </ymin>
   <ymax>
    342.8326517235964
   </ymax>
  </bndbox>
 </object>
 <folder>
  dataset
 </folder>
 <filename>
  ErithacusRubecula0625.jpg
 </filename>
</annotation>