<annotation>
 <path>
  Periparus_ater_1024.jpg
 </path>
 <source>
  <database>
   Unknown
  </database>
  <reviewresult>
  </reviewresult>
  <comment>
   <admin>
   </admin>
   <subord>
   </subord>
  </comment>
 </source>
 <size>
  <width>
   1024
  </width>
  <height>
   683
  </height>
  <depth>
   3
  </depth>
 </size>
 <segments>
  0
 </segments>
 <object>
  <name>
   PeriparusAter
  </name>
  <pose>
   Unspecified
  </pose>
  <truncated>
   0
  </truncated>
  <difficult>
   0
  </difficult>
  <bndbox>
   <xmin>
    480.56718232339426
   </xmin>
   <xmax>
    738.6721304905418
   </xmax>
   <ymin>
    245.10298439670837
   </ymin>
   <ymax>
    372.4036149406861
   </ymax>
  </bndbox>
 </object>
 <folder>
  dataset
 </folder>
 <filename>
  Periparus_ater_1024.jpg
 </filename>
</annotation>