<annotation>
 <path>
  Periparus_ater_23.jpg
 </path>
 <source>
  <database>
   Unknown
  </database>
  <reviewresult>
  </reviewresult>
  <comment>
   <admin>
   </admin>
   <subord>
   </subord>
  </comment>
 </source>
 <size>
  <width>
   867
  </width>
  <height>
   1024
  </height>
  <depth>
   3
  </depth>
 </size>
 <segments>
  0
 </segments>
 <object>
  <name>
   PeriparusAter
  </name>
  <pose>
   Unspecified
  </pose>
  <truncated>
   0
  </truncated>
  <difficult>
   0
  </difficult>
  <bndbox>
   <xmin>
    196.3976553259584
   </xmin>
   <xmax>
    626.8296041188339
   </xmax>
   <ymin>
    361.12510958046335
   </ymin>
   <ymax>
    676.6536144159187
   </ymax>
  </bndbox>
 </object>
 <folder>
  dataset
 </folder>
 <filename>
  Periparus_ater_23.jpg
 </filename>
</annotation>