<annotation>
 <path>
  Pica_pica_1150.jpg
 </path>
 <source>
  <database>
   Unknown
  </database>
  <reviewresult>
  </reviewresult>
  <comment>
   <admin>
   </admin>
   <subord>
   </subord>
  </comment>
 </source>
 <size>
  <width>
   1024
  </width>
  <height>
   768
  </height>
  <depth>
   3
  </depth>
 </size>
 <segments>
  0
 </segments>
 <object>
  <name>
   PicaPica
  </name>
  <pose>
   Unspecified
  </pose>
  <truncated>
   0
  </truncated>
  <difficult>
   0
  </difficult>
  <bndbox>
   <xmin>
    214.97134508114456
   </xmin>
   <xmax>
    408.26780093809526
   </xmax>
   <ymin>
    353.9258945701079
   </ymin>
   <ymax>
    500.24057296182764
   </ymax>
  </bndbox>
 </object>
 <object>
  <name>
   PicaPica
  </name>
  <pose>
   Unspecified
  </pose>
  <truncated>
   0
  </truncated>
  <difficult>
   0
  </difficult>
  <bndbox>
   <xmin>
    724.3880464541502
   </xmin>
   <xmax>
    869.3603883468631
   </xmax>
   <ymin>
    370.03393255818713
   </ymin>
   <ymax>
    567.3573979121577
   </ymax>
  </bndbox>
 </object>
 <folder>
  dataset
 </folder>
 <filename>
  Pica_pica_1150.jpg
 </filename>
</annotation>