<annotation>
 <path>
  Pica_pica_1020.jpg
 </path>
 <source>
  <database>
   Unknown
  </database>
  <reviewresult>
  </reviewresult>
  <comment>
   <admin>
   </admin>
   <subord>
   </subord>
  </comment>
 </source>
 <size>
  <width>
   704
  </width>
  <height>
   898
  </height>
  <depth>
   3
  </depth>
 </size>
 <segments>
  0
 </segments>
 <object>
  <name>
   PicaPica
  </name>
  <pose>
   Unspecified
  </pose>
  <truncated>
   0
  </truncated>
  <difficult>
   0
  </difficult>
  <bndbox>
   <xmin>
    113.06609387464694
   </xmin>
   <xmax>
    473.65236842672647
   </xmax>
   <ymin>
    369.531230460749
   </ymin>
   <ymax>
    492.2049114939307
   </ymax>
  </bndbox>
 </object>
 <folder>
  dataset
 </folder>
 <filename>
  Pica_pica_1020.jpg
 </filename>
</annotation>