<annotation>
 <path>
  Pica_pica_287.jpg
 </path>
 <source>
  <database>
   Unknown
  </database>
  <reviewresult>
  </reviewresult>
  <comment>
   <admin>
   </admin>
   <subord>
   </subord>
  </comment>
 </source>
 <size>
  <width>
   768
  </width>
  <height>
   1024
  </height>
  <depth>
   3
  </depth>
 </size>
 <segments>
  0
 </segments>
 <object>
  <name>
   PicaPica
  </name>
  <pose>
   Unspecified
  </pose>
  <truncated>
   0
  </truncated>
  <difficult>
   0
  </difficult>
  <bndbox>
   <xmin>
    216.15899827264843
   </xmin>
   <xmax>
    234.95170925874086
   </xmax>
   <ymin>
    592.7114776707381
   </ymin>
   <ymax>
    605.2399516614664
   </ymax>
  </bndbox>
 </object>
 <folder>
  dataset
 </folder>
 <filename>
  Pica_pica_287.jpg
 </filename>
</annotation>